manga_scrap/__init__.py
manga_scrap/excepciones.py
manga_scrap/modelos.py
manga_scrap/proveedores/__init__.py
manga_scrap/proveedores/mangaList.py
manga_scrap/proveedores/mangaStream.py
manga_scrap/proveedores/proveedor.py
manga_scrap/proveedores/prueba.py
manga_scrap-0.5.0.dist-info/WHEEL
manga_scrap-0.5.0.dist-info/METADATA
manga_scrap-0.5.0.dist-info/RECORD
