Metadata-Version: 2.1
Name: manga-scrap
Version: 0.5.0
Summary: A flexible and extensible library to scrap manga and convert it to usable models
Author: Andrés Riquelme
Author-email: andresfranco.rs@gmail.com
Requires-Python: >=3.9,<4.0
Classifier: Programming Language :: Python :: 3
Classifier: Programming Language :: Python :: 3.9
Requires-Dist: beautifulsoup4 (>=4.9.3,<5.0.0)
Requires-Dist: requests (>=2.26.0,<3.0.0)
